MANIFEST.in
README.md
setup.py
pyhs2/__init__.py
pyhs2/connections.py
pyhs2/cursor.py
pyhs2/error.py
pyhs2.egg-info/PKG-INFO
pyhs2.egg-info/SOURCES.txt
pyhs2.egg-info/dependency_links.txt
pyhs2.egg-info/requires.txt
pyhs2.egg-info/top_level.txt
pyhs2/TCLIService/TCLIService.py
pyhs2/TCLIService/__init__.py
pyhs2/TCLIService/constants.py
pyhs2/TCLIService/ttypes.py
pyhs2/cloudera/__init__.py
pyhs2/cloudera/thrift_sasl.py