Metadata-Version: 1.0
Name: pyhs2
Version: 0.4.1
Summary: Python Hive Server 2 Client Driver
Home-page: https://github.com/BradRuderman/pyhs2
Author: Brad Ruderman
Author-email: bradruderman@gmail.com
License: LICENSE.txt
Platform: UNKNOWN
